README.md
setup.cfg
setup.py
predictiveness_curve/__init__.py
predictiveness_curve/base.py
predictiveness_curve.egg-info/PKG-INFO
predictiveness_curve.egg-info/SOURCES.txt
predictiveness_curve.egg-info/dependency_links.txt
predictiveness_curve.egg-info/requires.txt
predictiveness_curve.egg-info/top_level.txt