Metadata-Version: 2.1
Name: predictiveness-curve
Version: 0.2.2
Summary: Plot predictiveness curve
Home-page: https://github.com/yamasakih/predictiveness-curve
Author: Hiroyuki Yamasaki
Author-email: yamasaki.phone@gmail.com
License: MIT
Platform: UNKNOWN
Classifier: License :: OSI Approved :: MIT License
Requires-Python: >=3.6
